genlm/backend/__init__.py
genlm/backend/cache.py
genlm/backend/llm/__init__.py
genlm/backend/llm/base.py
genlm/backend/llm/hf.py
genlm/backend/llm/mlx.py
genlm/backend/llm/vllm.py
genlm/backend/tokenization/__init__.py
genlm/backend/tokenization/bytes.py
genlm/backend/tokenization/vocab.py
genlm/backend/trie/__init__.py
genlm/backend/trie/async_impl.py
genlm/backend/trie/base.py
genlm/backend/trie/parallel.py
genlm_backend-0.1.8.dist-info/licenses/LICENSE
genlm_backend-0.1.8.dist-info/METADATA
genlm_backend-0.1.8.dist-info/WHEEL
genlm_backend-0.1.8.dist-info/top_level.txt
genlm_backend-0.1.8.dist-info/RECORD
