Metadata-Version: 2.4
Name: genlm-backend
Version: 0.1.8
Author: Ben LeBrun
Requires-Python: >=3.10
License-File: LICENSE
Requires-Dist: torch
Requires-Dist: transformers<5.0.0.rc0,>=4.36.0
Requires-Dist: sentencepiece
Requires-Dist: protobuf
Requires-Dist: accelerate
Requires-Dist: bitsandbytes; sys_platform == "linux"
Requires-Dist: numba
Requires-Dist: vllm<=0.10.0,>=0.6.6; sys_platform == "linux"
Requires-Dist: triton>=3.2.0; sys_platform == "linux"
Provides-Extra: mlx
Requires-Dist: mlx; extra == "mlx"
Requires-Dist: mlx-lm; extra == "mlx"
Provides-Extra: lora
Requires-Dist: peft; extra == "lora"
Provides-Extra: docs
Requires-Dist: mkdocs; extra == "docs"
Requires-Dist: mkdocstrings[python]; extra == "docs"
Requires-Dist: mkdocs-material; extra == "docs"
Requires-Dist: mkdocs-gen-files; extra == "docs"
Requires-Dist: mkdocs-literate-nav; extra == "docs"
Requires-Dist: mkdocs-section-index; extra == "docs"
Dynamic: license-file
